{
    "name": "Design Event",
    "headers": [
        "Place",
        "Car Num",
        "Team",
        "Raw Score",
        "Penalty",
        "Score"
    ],
    "content": {
        "1": [
            {
                "Place": 1,
                "Car Num": 19,
                "Team": "Ecole De Technologie Superieure",
                "Raw Score": 150.0,
                "Penalty": 0,
                "Score": 0.0
            }
        ],
        "2": [
            {
                "Place": 2,
                "Car Num": 9,
                "Team": "Univ of Florida",
                "Raw Score": 140.0,
                "Penalty": 0,
                "Score": 0.0
            }
        ],
        "3": [
            {
                "Place": 3,
                "Car Num": 13,
                "Team": "Univ of Wisconsin - Madison",
                "Raw Score": 130.0,
                "Penalty": 0,
                "Score": 0.0
            }
        ],
        "4": [
            {
                "Place": 4,
                "Car Num": 5,
                "Team": "Univ of Akron",
                "Raw Score": 125.0,
                "Penalty": 0,
                "Score": 0.0
            },
            {
                "Place": 4,
                "Car Num": 7,
                "Team": "Auburn Univ",
                "Raw Score": 125.0,
                "Penalty": 0,
                "Score": 0.0
            },
            {
                "Place": 4,
                "Car Num": 11,
                "Team": "Universidade Estadual de Campinas",
                "Raw Score": 125.0,
                "Penalty": 0,
                "Score": 0.0
            }
        ],
        "7": [
            {
                "Place": 7,
                "Car Num": 8,
                "Team": "Univ of Michigan - Ann Arbor",
                "Raw Score": 115.0,
                "Penalty": 0,
                "Score": 0.0
            },
            {
                "Place": 7,
                "Car Num": 14,
                "Team": "Univ of Kansas - Lawrence",
                "Raw Score": 115.0,
                "Penalty": 0,
                "Score": 0.0
            },
            {
                "Place": 7,
                "Car Num": 16,
                "Team": "Graz Technical Univ",
                "Raw Score": 115.0,
                "Penalty": 0,
                "Score": 0.0
            },
            {
                "Place": 7,
                "Car Num": 71,
                "Team": "Univ of Pittsburgh - Pittsburgh",
                "Raw Score": 115.0,
                "Penalty": 0,
                "Score": 0.0
            },
            {
                "Place": 7,
                "Car Num": 129,
                "Team": "Univ of Texas - Arlington",
                "Raw Score": 115.0,
                "Penalty": 0,
                "Score": 0.0
            }
        ],
        "12": [
            {
                "Place": 12,
                "Car Num": 1,
                "Team": "Oregon State Univ",
                "Raw Score": 105.0,
                "Penalty": 0,
                "Score": 0.0
            },
            {
                "Place": 12,
                "Car Num": 12,
                "Team": "Michigan State Univ",
                "Raw Score": 105.0,
                "Penalty": 0,
                "Score": 0.0
            },
            {
                "Place": 12,
                "Car Num": 25,
                "Team": "Georgia Institute of Technology",
                "Raw Score": 105.0,
                "Penalty": 0,
                "Score": 0.0
            },
            {
                "Place": 12,
                "Car Num": 46,
                "Team": "McGill Univ",
                "Raw Score": 105.0,
                "Penalty": 0,
                "Score": 0.0
            },
            {
                "Place": 12,
                "Car Num": 115,
                "Team": "Rochester Institute of Technology",
                "Raw Score": 105.0,
                "Penalty": 0,
                "Score": 0.0
            },
            {
                "Place": 12,
                "Car Num": 117,
                "Team": "Western University",
                "Raw Score": 105.0,
                "Penalty": 0,
                "Score": 0.0
            }
        ],
        "18": [
            {
                "Place": 18,
                "Car Num": 18,
                "Team": "San Jose State University",
                "Raw Score": 100.0,
                "Penalty": 0,
                "Score": 0.0
            },
            {
                "Place": 18,
                "Car Num": 21,
                "Team": "Univ of Illinois - Urbana Champaign",
                "Raw Score": 100.0,
                "Penalty": 0,
                "Score": 0.0
            },
            {
                "Place": 18,
                "Car Num": 38,
                "Team": "National Univ of Singapore",
                "Raw Score": 100.0,
                "Penalty": 0,
                "Score": 0.0
            },
            {
                "Place": 18,
                "Car Num": 51,
                "Team": "Univ of Cincinnati",
                "Raw Score": 100.0,
                "Penalty": 0,
                "Score": 0.0
            },
            {
                "Place": 18,
                "Car Num": 53,
                "Team": "Kookmin Univ",
                "Raw Score": 100.0,
                "Penalty": 0,
                "Score": 0.0
            },
            {
                "Place": 18,
                "Car Num": 62,
                "Team": "Ohio State Univ",
                "Raw Score": 100.0,
                "Penalty": 0,
                "Score": 0.0
            },
            {
                "Place": 18,
                "Car Num": 70,
                "Team": "Kennesaw State University",
                "Raw Score": 100.0,
                "Penalty": 0,
                "Score": 0.0
            },
            {
                "Place": 18,
                "Car Num": 85,
                "Team": "Villanova Univ",
                "Raw Score": 100.0,
                "Penalty": 0,
                "Score": 0.0
            },
            {
                "Place": 18,
                "Car Num": 101,
                "Team": "Wroclaw University of Technology",
                "Raw Score": 100.0,
                "Penalty": 0,
                "Score": 0.0
            },
            {
                "Place": 18,
                "Car Num": 110,
                "Team": "Virginia Tech",
                "Raw Score": 100.0,
                "Penalty": 0,
                "Score": 0.0
            },
            {
                "Place": 18,
                "Car Num": 126,
                "Team": "Cornell Univ",
                "Raw Score": 100.0,
                "Penalty": 0,
                "Score": 0.0
            }
        ],
        "29": [
            {
                "Place": 29,
                "Car Num": 125,
                "Team": "Purdue Univ - W Lafayette",
                "Raw Score": 105.0,
                "Penalty": 10,
                "Score": 0.0
            }
        ],
        "30": [
            {
                "Place": 30,
                "Car Num": 50,
                "Team": "Missouri University of Science and Tech",
                "Raw Score": 100.0,
                "Penalty": 10,
                "Score": 0.0
            }
        ],
        "31": [
            {
                "Place": 31,
                "Car Num": 15,
                "Team": "Kettering Univ",
                "Raw Score": 85.0,
                "Penalty": 0,
                "Score": 0.0
            },
            {
                "Place": 31,
                "Car Num": 17,
                "Team": "Univ of Toledo",
                "Raw Score": 85.0,
                "Penalty": 0,
                "Score": 0.0
            },
            {
                "Place": 31,
                "Car Num": 29,
                "Team": "Lehigh Univ",
                "Raw Score": 85.0,
                "Penalty": 0,
                "Score": 0.0
            },
            {
                "Place": 31,
                "Car Num": 30,
                "Team": "Univ of Missouri",
                "Raw Score": 85.0,
                "Penalty": 0,
                "Score": 0.0
            },
            {
                "Place": 31,
                "Car Num": 36,
                "Team": "Univ of North Florida",
                "Raw Score": 85.0,
                "Penalty": 0,
                "Score": 0.0
            },
            {
                "Place": 31,
                "Car Num": 37,
                "Team": "Univ of Connecticut",
                "Raw Score": 85.0,
                "Penalty": 0,
                "Score": 0.0
            },
            {
                "Place": 31,
                "Car Num": 40,
                "Team": "Univ of Central Florida",
                "Raw Score": 85.0,
                "Penalty": 0,
                "Score": 0.0
            },
            {
                "Place": 31,
                "Car Num": 43,
                "Team": "Columbia Univ",
                "Raw Score": 85.0,
                "Penalty": 0,
                "Score": 0.0
            },
            {
                "Place": 31,
                "Car Num": 47,
                "Team": "Univ of South Florida",
                "Raw Score": 85.0,
                "Penalty": 0,
                "Score": 0.0
            },
            {
                "Place": 31,
                "Car Num": 49,
                "Team": "Univ of Toronto",
                "Raw Score": 85.0,
                "Penalty": 0,
                "Score": 0.0
            },
            {
                "Place": 31,
                "Car Num": 58,
                "Team": "Polytechnique Montréal",
                "Raw Score": 85.0,
                "Penalty": 0,
                "Score": 0.0
            },
            {
                "Place": 31,
                "Car Num": 59,
                "Team": "Univ of Minnesota - Twin Cities",
                "Raw Score": 85.0,
                "Penalty": 0,
                "Score": 0.0
            },
            {
                "Place": 31,
                "Car Num": 69,
                "Team": "Univ of Waterloo",
                "Raw Score": 85.0,
                "Penalty": 0,
                "Score": 0.0
            },
            {
                "Place": 31,
                "Car Num": 72,
                "Team": "Univ of Michigan - Dearborn",
                "Raw Score": 85.0,
                "Penalty": 0,
                "Score": 0.0
            },
            {
                "Place": 31,
                "Car Num": 73,
                "Team": "Saginaw Valley State Univ",
                "Raw Score": 85.0,
                "Penalty": 0,
                "Score": 0.0
            },
            {
                "Place": 31,
                "Car Num": 78,
                "Team": "Universite Du Quebec-Chicoutimi",
                "Raw Score": 85.0,
                "Penalty": 0,
                "Score": 0.0
            },
            {
                "Place": 31,
                "Car Num": 82,
                "Team": "Clemson Univ",
                "Raw Score": 85.0,
                "Penalty": 0,
                "Score": 0.0
            },
            {
                "Place": 31,
                "Car Num": 83,
                "Team": "Oakland University",
                "Raw Score": 85.0,
                "Penalty": 0,
                "Score": 0.0
            },
            {
                "Place": 31,
                "Car Num": 86,
                "Team": "Cooper Union",
                "Raw Score": 85.0,
                "Penalty": 0,
                "Score": 0.0
            },
            {
                "Place": 31,
                "Car Num": 96,
                "Team": "Penn State Univ - University Park",
                "Raw Score": 85.0,
                "Penalty": 0,
                "Score": 0.0
            },
            {
                "Place": 31,
                "Car Num": 109,
                "Team": "Univ of Oklahoma",
                "Raw Score": 85.0,
                "Penalty": 0,
                "Score": 0.0
            },
            {
                "Place": 31,
                "Car Num": 114,
                "Team": "Michigan Tech Univ",
                "Raw Score": 85.0,
                "Penalty": 0,
                "Score": 0.0
            },
            {
                "Place": 31,
                "Car Num": 120,
                "Team": "Univ of Maryland - College Park",
                "Raw Score": 85.0,
                "Penalty": 0,
                "Score": 0.0
            },
            {
                "Place": 31,
                "Car Num": 123,
                "Team": "Florida Atlantic Univ",
                "Raw Score": 85.0,
                "Penalty": 0,
                "Score": 0.0
            },
            {
                "Place": 31,
                "Car Num": 127,
                "Team": "Univ of Manitoba",
                "Raw Score": 85.0,
                "Penalty": 0,
                "Score": 0.0
            }
        ],
        "56": [
            {
                "Place": 56,
                "Car Num": 106,
                "Team": "South Dakota State Univ",
                "Raw Score": 85.0,
                "Penalty": 10,
                "Score": 0.0
            }
        ],
        "57": [
            {
                "Place": 57,
                "Car Num": 22,
                "Team": "US Naval Academy",
                "Raw Score": 70.0,
                "Penalty": 0,
                "Score": 0.0
            },
            {
                "Place": 57,
                "Car Num": 24,
                "Team": "Brown Univ",
                "Raw Score": 70.0,
                "Penalty": 0,
                "Score": 0.0
            },
            {
                "Place": 57,
                "Car Num": 26,
                "Team": "Georgia Southern Univ",
                "Raw Score": 70.0,
                "Penalty": 0,
                "Score": 0.0
            },
            {
                "Place": 57,
                "Car Num": 27,
                "Team": "Louisiana State Univ",
                "Raw Score": 70.0,
                "Penalty": 0,
                "Score": 0.0
            },
            {
                "Place": 57,
                "Car Num": 32,
                "Team": "Rose Hulman Inst of Tech",
                "Raw Score": 70.0,
                "Penalty": 0,
                "Score": 0.0
            },
            {
                "Place": 57,
                "Car Num": 33,
                "Team": "West Virginia Univ",
                "Raw Score": 70.0,
                "Penalty": 0,
                "Score": 0.0
            },
            {
                "Place": 57,
                "Car Num": 41,
                "Team": "Old Dominion Univ",
                "Raw Score": 70.0,
                "Penalty": 0,
                "Score": 0.0
            },
            {
                "Place": 57,
                "Car Num": 48,
                "Team": "Washington Univ - St Louis",
                "Raw Score": 70.0,
                "Penalty": 0,
                "Score": 0.0
            },
            {
                "Place": 57,
                "Car Num": 55,
                "Team": "Universidad Central de Venezuela",
                "Raw Score": 70.0,
                "Penalty": 0,
                "Score": 0.0
            },
            {
                "Place": 57,
                "Car Num": 57,
                "Team": "Texas Tech Univ",
                "Raw Score": 70.0,
                "Penalty": 0,
                "Score": 0.0
            },
            {
                "Place": 57,
                "Car Num": 63,
                "Team": "Duke Univ",
                "Raw Score": 70.0,
                "Penalty": 0,
                "Score": 0.0
            },
            {
                "Place": 57,
                "Car Num": 64,
                "Team": "Univ of Alabama - Tuscaloosa",
                "Raw Score": 70.0,
                "Penalty": 0,
                "Score": 0.0
            },
            {
                "Place": 57,
                "Car Num": 65,
                "Team": "Minnesota State University - Mankato",
                "Raw Score": 70.0,
                "Penalty": 0,
                "Score": 0.0
            },
            {
                "Place": 57,
                "Car Num": 68,
                "Team": "Lakehead Univ",
                "Raw Score": 70.0,
                "Penalty": 0,
                "Score": 0.0
            },
            {
                "Place": 57,
                "Car Num": 74,
                "Team": "North Dakota State Univ",
                "Raw Score": 70.0,
                "Penalty": 0,
                "Score": 0.0
            },
            {
                "Place": 57,
                "Car Num": 77,
                "Team": "Cegep du Vieux - Montreal",
                "Raw Score": 70.0,
                "Penalty": 0,
                "Score": 0.0
            },
            {
                "Place": 57,
                "Car Num": 81,
                "Team": "Universidad Simon Bolivar",
                "Raw Score": 70.0,
                "Penalty": 0,
                "Score": 0.0
            },
            {
                "Place": 57,
                "Car Num": 94,
                "Team": "Oklahoma State Univ",
                "Raw Score": 70.0,
                "Penalty": 0,
                "Score": 0.0
            },
            {
                "Place": 57,
                "Car Num": 95,
                "Team": "Wayne State Univ",
                "Raw Score": 70.0,
                "Penalty": 0,
                "Score": 0.0
            },
            {
                "Place": 57,
                "Car Num": 97,
                "Team": "Univ of Guelph",
                "Raw Score": 70.0,
                "Penalty": 0,
                "Score": 0.0
            },
            {
                "Place": 57,
                "Car Num": 99,
                "Team": "York College of Pa",
                "Raw Score": 70.0,
                "Penalty": 0,
                "Score": 0.0
            },
            {
                "Place": 57,
                "Car Num": 100,
                "Team": "Northern Illinois Univ",
                "Raw Score": 70.0,
                "Penalty": 0,
                "Score": 0.0
            },
            {
                "Place": 57,
                "Car Num": 102,
                "Team": "Florida Inst of Tech",
                "Raw Score": 70.0,
                "Penalty": 0,
                "Score": 0.0
            },
            {
                "Place": 57,
                "Car Num": 103,
                "Team": "Northwestern Univ",
                "Raw Score": 70.0,
                "Penalty": 0,
                "Score": 0.0
            },
            {
                "Place": 57,
                "Car Num": 107,
                "Team": "Univ of Utah",
                "Raw Score": 70.0,
                "Penalty": 0,
                "Score": 0.0
            },
            {
                "Place": 57,
                "Car Num": 116,
                "Team": "Universidad Metropolitana",
                "Raw Score": 70.0,
                "Penalty": 0,
                "Score": 0.0
            },
            {
                "Place": 57,
                "Car Num": 119,
                "Team": "Univ of Victoria",
                "Raw Score": 70.0,
                "Penalty": 0,
                "Score": 0.0
            },
            {
                "Place": 57,
                "Car Num": 122,
                "Team": "Indiana Univ Purdue Univ Indianapolis",
                "Raw Score": 70.0,
                "Penalty": 0,
                "Score": 0.0
            },
            {
                "Place": 57,
                "Car Num": 134,
                "Team": "Mississippi State Univ",
                "Raw Score": 70.0,
                "Penalty": 0,
                "Score": 0.0
            }
        ],
        "86": [
            {
                "Place": 86,
                "Car Num": 76,
                "Team": "Universite Du Quebec a Trois-Rivieres",
                "Raw Score": 85.0,
                "Penalty": 20,
                "Score": 0.0
            }
        ],
        "87": [
            {
                "Place": 87,
                "Car Num": 20,
                "Team": "Worcester Polytechnic Inst",
                "Raw Score": 60.0,
                "Penalty": 0,
                "Score": 0.0
            },
            {
                "Place": 87,
                "Car Num": 23,
                "Team": "Ferris State University",
                "Raw Score": 60.0,
                "Penalty": 0,
                "Score": 0.0
            },
            {
                "Place": 87,
                "Car Num": 31,
                "Team": "Bradley Univ",
                "Raw Score": 60.0,
                "Penalty": 0,
                "Score": 0.0
            },
            {
                "Place": 87,
                "Car Num": 35,
                "Team": "Southern Illinois Univ - Edwardville",
                "Raw Score": 60.0,
                "Penalty": 0,
                "Score": 0.0
            },
            {
                "Place": 87,
                "Car Num": 42,
                "Team": "Florida International Univ",
                "Raw Score": 60.0,
                "Penalty": 0,
                "Score": 0.0
            },
            {
                "Place": 87,
                "Car Num": 44,
                "Team": "Western Michigan Univ",
                "Raw Score": 60.0,
                "Penalty": 0,
                "Score": 0.0
            },
            {
                "Place": 87,
                "Car Num": 45,
                "Team": "Tennessee Tech Univ",
                "Raw Score": 60.0,
                "Penalty": 0,
                "Score": 0.0
            },
            {
                "Place": 87,
                "Car Num": 52,
                "Team": "Colorado Mesa University",
                "Raw Score": 60.0,
                "Penalty": 0,
                "Score": 0.0
            },
            {
                "Place": 87,
                "Car Num": 56,
                "Team": "Central Michigan Univ",
                "Raw Score": 60.0,
                "Penalty": 0,
                "Score": 0.0
            },
            {
                "Place": 87,
                "Car Num": 60,
                "Team": "Univ of Illinois - Chicago",
                "Raw Score": 60.0,
                "Penalty": 0,
                "Score": 0.0
            },
            {
                "Place": 87,
                "Car Num": 67,
                "Team": "Queen's Univ - Ontario Canada",
                "Raw Score": 60.0,
                "Penalty": 0,
                "Score": 0.0
            },
            {
                "Place": 87,
                "Car Num": 79,
                "Team": "St Cloud State Univ",
                "Raw Score": 60.0,
                "Penalty": 0,
                "Score": 0.0
            },
            {
                "Place": 87,
                "Car Num": 88,
                "Team": "Dalhousie Univ",
                "Raw Score": 60.0,
                "Penalty": 0,
                "Score": 0.0
            },
            {
                "Place": 87,
                "Car Num": 90,
                "Team": "Univ of North Carolina - Charlotte",
                "Raw Score": 60.0,
                "Penalty": 0,
                "Score": 0.0
            },
            {
                "Place": 87,
                "Car Num": 104,
                "Team": "Washington State Univ",
                "Raw Score": 60.0,
                "Penalty": 0,
                "Score": 0.0
            },
            {
                "Place": 87,
                "Car Num": 111,
                "Team": "Universidad Autonoma Estado Mexico",
                "Raw Score": 60.0,
                "Penalty": 0,
                "Score": 0.0
            },
            {
                "Place": 87,
                "Car Num": 121,
                "Team": "Lawrence Technological Univ",
                "Raw Score": 60.0,
                "Penalty": 0,
                "Score": 0.0
            }
        ],
        "104": [
            {
                "Place": 104,
                "Car Num": 61,
                "Team": "Rutgers Univ",
                "Raw Score": 60.0,
                "Penalty": 10,
                "Score": 0.0
            },
            {
                "Place": 104,
                "Car Num": 66,
                "Team": "North Carolina State Univ - Raleigh",
                "Raw Score": 60.0,
                "Penalty": 10,
                "Score": 0.0
            },
            {
                "Place": 104,
                "Car Num": 113,
                "Team": "Temple Univ",
                "Raw Score": 60.0,
                "Penalty": 10,
                "Score": 0.0
            }
        ],
        "107": [
            {
                "Place": 107,
                "Car Num": 54,
                "Team": "Univ of Evansville",
                "Raw Score": 70.0,
                "Penalty": 35,
                "Score": 0.0
            }
        ],
        "108": [
            {
                "Place": 108,
                "Car Num": 93,
                "Team": "Univ of St Thomas",
                "Raw Score": 60.0,
                "Penalty": 35,
                "Score": 0.0
            }
        ]
    }
}